generator/__init__.py
generator/management/__init__.py
generator/management/commands/__init__.py
generator/management/commands/generate.py
generator/management/commands/generate_form.py
generator/management/commands/api/__init__.py
generator/management/commands/api/delete.py
generator/management/commands/api/get.py
generator/management/commands/api/patch.py
generator/management/commands/api/post.py
generator/management/commands/api/put.py
generator/management/commands/form/__init__.py
generator/management/commands/form/create_form.py
generator/management/commands/form/delete_form.py
generator/management/commands/form/details_form.py
generator/management/commands/form/imports.py
generator/management/commands/form/post_form.py
generator/management/commands/form/read_form.py
generator/management/commands/form/update_form.py
generator/management/commands/urls/__init__.py
generator/management/commands/urls/build.py
generator/management/commands/urls/build_url_form.py
generator/management/commands/urls/create_urls.py
wild_generator-0.0.1.dist-info/licenses/LICENSE
wild_generator-0.0.1.dist-info/METADATA
wild_generator-0.0.1.dist-info/WHEEL
wild_generator-0.0.1.dist-info/top_level.txt
wild_generator-0.0.1.dist-info/RECORD
