Metadata-Version: 2.4
Name: wild-generator
Version: 0.0.1
Summary: Gerador de código para CRUDs completos no Django, incluindo Views, Forms e URLs.
Home-page: https://github.com/Alyffantonio/code_generator
Author: Alyff antonio barbosa da silva
Author-email: alyffantonio@gmail.com
License: MIT
Classifier: Environment :: Web Environment
Classifier: Framework :: Django
Classifier: Framework :: Django :: 4.2
Classifier: Intended Audience :: Developers
Classifier: Operating System :: OS Independent
Classifier: Programming Language :: Python
Classifier: Programming Language :: Python :: 3
Classifier: Programming Language :: Python :: 3.8
Classifier: Programming Language :: Python :: 3.9
Classifier: Programming Language :: Python :: 3.10
Classifier: Programming Language :: Python :: 3.11
Requires-Python: >=3.8
License-File: LICENSE
Requires-Dist: Django>=4.2
Dynamic: license-file
